ilc_models/__init__.py
ilc_models/py.typed
ilc_models-0.2.2.dist-info/METADATA
ilc_models-0.2.2.dist-info/WHEEL
ilc_models-0.2.2.dist-info/licenses/LICENSE.txt
ilc_models-0.2.2.dist-info/RECORD
