Metadata-Version: 2.4
Name: ilc-models
Version: 0.2.2
Summary: Data models for the ILC project
Project-URL: Repository, https://github.com/fourtreestech/ilc-models
Author-email: Neil Martin <neil@fourtrees.tech>
License-Expression: MIT
License-File: LICENSE.txt
Classifier: Development Status :: 4 - Beta
Classifier: Intended Audience :: Developers
Classifier: Natural Language :: English
Classifier: Programming Language :: Python :: 3.12
Classifier: Programming Language :: Python :: 3.13
Classifier: Topic :: Software Development :: Libraries
Classifier: Typing :: Typed
Requires-Python: >=3.12
Requires-Dist: pydantic>=2.12.5
